MailToolsBox/__init__.py
MailToolsBox/imapClient.py
MailToolsBox/mailSender.py
mailtoolsbox-1.1.0.dist-info/licenses/LICENSE.txt
mailtoolsbox-1.1.0.dist-info/METADATA
mailtoolsbox-1.1.0.dist-info/WHEEL
mailtoolsbox-1.1.0.dist-info/top_level.txt
mailtoolsbox-1.1.0.dist-info/RECORD
