Metadata-Version: 2.4
Name: MailToolsBox
Version: 1.1.0
Summary: Modern sync and async SMTP with optional TLS/SSL, OAuth2 XOAUTH2, Jinja2 templates, and attachments.
Home-page: https://github.com/rambod/MailToolsBox
Download-URL: https://github.com/rambod/MailToolsBox/archive/refs/tags/v1.1.0.tar.gz
Author: Rambod Ghashghai
Author-email: gh.rambod@gmail.com
License: MIT
Project-URL: Source, https://github.com/rambod/MailToolsBox
Project-URL: Issues, https://github.com/rambod/MailToolsBox/issues
Keywords: mail,smtp,email,tls,ssl,oauth2,xoauth2,jinja2,asyncio,aiosmtplib,email-validation
Classifier: Development Status :: 5 - Production/Stable
Classifier: Intended Audience :: Developers
Classifier: Topic :: Communications :: Email
Classifier: License :: OSI Approved :: MIT License
Classifier: Programming Language :: Python
Classifier: Programming Language :: Python :: 3 :: Only
Classifier: Programming Language :: Python :: 3.8
Classifier: Programming Language :: Python :: 3.9
Classifier: Programming Language :: Python :: 3.10
Classifier: Programming Language :: Python :: 3.11
Classifier: Programming Language :: Python :: 3.12
Classifier: Typing :: Typed
Requires-Python: >=3.8
License-File: LICENSE.txt
Requires-Dist: Jinja2>=3.0.2
Requires-Dist: email-validator>=2.0.0
Requires-Dist: aiosmtplib>=2.0.0
Requires-Dist: aiofiles>=23.0.0
Provides-Extra: dev
Requires-Dist: pytest>=7.0; extra == "dev"
Requires-Dist: pytest-asyncio>=0.20; extra == "dev"
Requires-Dist: mypy>=1.0; extra == "dev"
Requires-Dist: black>=24.0; extra == "dev"
Requires-Dist: ruff>=0.5; extra == "dev"
Provides-Extra: docs
Requires-Dist: mkdocs>=1.5; extra == "docs"
Requires-Dist: mkdocs-material>=9.5; extra == "docs"
Dynamic: author
Dynamic: author-email
Dynamic: classifier
Dynamic: description
Dynamic: description-content-type
Dynamic: download-url
Dynamic: home-page
Dynamic: keywords
Dynamic: license
Dynamic: license-file
Dynamic: project-url
Dynamic: provides-extra
Dynamic: requires-dist
Dynamic: requires-python
Dynamic: summary
